{
  "created_at": "Mon Jul 17 05:44:16 +0000 2017",
  "id": 886823848720474100,
  "id_str": "886823848720474112",
  "text": "Arya 🙌 #GameofThrones7",
  "truncated": false,
  "entities": {
    "hashtags": [
      {
        "text": "GameofThrones7",
        "indices": [
          7,
          22
        ]
      }
    ],
    "symbols": [],
    "user_mentions": [],
    "urls": []
  },
  "metadata": {
    "iso_language_code": "en",
    "result_type": "recent"
  },
  "source": "<a href=\"http://twitter.com/download/iphone\" rel=\"nofollow\">Twitter for iPhone</a>",
  "in_reply_to_status_id": null,
  "in_reply_to_status_id_str": null,
  "in_reply_to_user_id": null,
  "in_reply_to_user_id_str": null,
  "in_reply_to_screen_name": null,
  "user": {
    "id": 1059194370,
    "id_str": "1059194370",
    "name": "Kobe Bryant",
    "screen_name": "kobebryant",
    "location": "",
    "description": "CEO Kobe Inc. Publisher. Investor. Producer.",
    "url": "https://t.co/MlnQXV0IoY",
    "entities": {
      "url": {
        "urls": [
          {
            "url": "https://t.co/MlnQXV0IoY",
            "expanded_url": "http://www.kobebryant.com",
            "display_url": "kobebryant.com",
            "indices": [
              0,
              23
            ]
          }
        ]
      },
      "description": {
        "urls": []
      }
    },
    "protected": false,
    "followers_count": 12110275,
    "friends_count": 324,
    "listed_count": 15979,
    "created_at": "Fri Jan 04 01:09:40 +0000 2013",
    "favourites_count": 6,
    "utc_offset": -25200,
    "time_zone": "Pacific Time (US & Canada)",
    "geo_enabled": false,
    "verified": true,
    "statuses_count": 1278,
    "lang": "en",
    "contributors_enabled": false,
    "is_translator": false,
    "is_translation_enabled": true,
    "profile_background_color": "C0DEED",
    "profile_background_image_url": "http://abs.twimg.com/images/themes/theme1/bg.png",
    "profile_background_image_url_https": "https://abs.twimg.com/images/themes/theme1/bg.png",
    "profile_background_tile": false,
    "profile_image_url": "http://pbs.twimg.com/profile_images/847230346546487296/c91SRFL0_normal.jpg",
    "profile_image_url_https": "https://pbs.twimg.com/profile_images/847230346546487296/c91SRFL0_normal.jpg",
    "profile_link_color": "1DA1F2",
    "profile_sidebar_border_color": "C0DEED",
    "profile_sidebar_fill_color": "DDEEF6",
    "profile_text_color": "333333",
    "profile_use_background_image": true,
    "has_extended_profile": false,
    "default_profile": true,
    "default_profile_image": false,
    "following": true,
    "follow_request_sent": false,
    "notifications": false,
    "translator_type": "none"
  },
  "geo": null,
  "coordinates": null,
  "place": null,
  "contributors": null,
  "is_quote_status": false,
  "retweet_count": 10131,
  "favorite_count": 32888,
  "favorited": false,
  "retweeted": false,
  "lang": "en"
}
